{
  "Slayer (Axe)": {
    "Name": "Slayer (Axe)",
    "Description": "Triple Weapon Might when using this weapon against an opponent with this Weapon",
    "Weapon": "All",
    "Level": "3",
    "Max Level": "3",
    "Type": "",
    "Might": "0",
    "Accuracy": "0",
    "Critical": "0",
    "Dodge": "0",
    "RangeMin": "0",
    "RangeMax": "0",
    "str": "0",
    "int": "0",
    "dex": "0",
    "spd": "0",
    "luk": "0",
    "con": "0",
    "wis": "0",
    "AttackCount": "0",
    "RiposteCount": "0",
    "ftAttackCount": "0",
    "ftRiposteCount": "0",
    "AttackPriority": "0",
    "RipostePriority": "0",
    "ftAttackPriority": "0",
    "ftRipostePriority": "0",
    "SkillSuccess": "0",
    "GreatSkillSuccess": "0",
    "GreatSkillDamage": "0",
    "Effect": "Slayer-Axe",
    "Slayer": "Axe"
  },
  "Healing": {
    "Name": "Healing",
    "Description": "The weapon can be used as a staff, and can heal an Ally by Might + INT HP",
    "Weapon": "All",
    "Level": "1",
    "Max Level": "1",
    "Type": "",
    "Might": "0",
    "Accuracy": "0",
    "Critical": "0",
    "Dodge": "0",
    "RangeMin": "0",
    "RangeMax": "0",
    "str": "0",
    "int": "0",
    "dex": "0",
    "spd": "0",
    "luk": "0",
    "con": "0",
    "wis": "0",
    "AttackCount": "0",
    "RiposteCount": "0",
    "ftAttackCount": "0",
    "ftRiposteCount": "0",
    "AttackPriority": "0",
    "RipostePriority": "0",
    "ftAttackPriority": "0",
    "ftRipostePriority": "0",
    "SkillSuccess": "0",
    "GreatSkillSuccess": "0",
    "GreatSkillDamage": "0",
    "Effect": "-",
    "Slayer": ""
  },
  "Reaver": {
    "Name": "Reaver",
    "Description": "Reverse the direction of the Weapon Triangle",
    "Weapon": "All",
    "Level": "2",
    "Max Level": "2",
    "Type": "",
    "Might": "0",
    "Accuracy": "0",
    "Critical": "0",
    "Dodge": "0",
    "RangeMin": "0",
    "RangeMax": "0",
    "str": "0",
    "int": "0",
    "dex": "0",
    "spd": "0",
    "luk": "0",
    "con": "0",
    "wis": "0",
    "AttackCount": "0",
    "RiposteCount": "0",
    "ftAttackCount": "0",
    "ftRiposteCount": "0",
    "AttackPriority": "0",
    "RipostePriority": "0",
    "ftAttackPriority": "0",
    "ftRipostePriority": "0",
    "SkillSuccess": "0",
    "GreatSkillSuccess": "0",
    "GreatSkillDamage": "0",
    "Effect": "Reaver",
    "Slayer": ""
  },
  "Slayer (Ride)": {
    "Name": "Slayer (Ride)",
    "Description": "Triple Weapon Might when using this weapon against an opponent with this Skill",
    "Weapon": "All",
    "Level": "2",
    "Max Level": "2",
    "Type": "",
    "Might": "0",
    "Accuracy": "0",
    "Critical": "0",
    "Dodge": "0",
    "RangeMin": "0",
    "RangeMax": "0",
    "str": "0",
    "int": "0",
    "dex": "0",
    "spd": "0",
    "luk": "0",
    "con": "0",
    "wis": "0",
    "AttackCount": "0",
    "RiposteCount": "0",
    "ftAttackCount": "0",
    "ftRiposteCount": "0",
    "AttackPriority": "0",
    "RipostePriority": "0",
    "ftAttackPriority": "0",
    "ftRipostePriority": "0",
    "SkillSuccess": "0",
    "GreatSkillSuccess": "0",
    "GreatSkillDamage": "0",
    "Effect": "Slayer-Ride",
    "Slayer": "Ride"
  },
  "Slayer (Light)": {
    "Name": "Slayer (Light)",
    "Description": "Triple Weapon Might when using this weapon against an opponent with this Weapon",
    "Weapon": "All",
    "Level": "3",
    "Max Level": "3",
    "Type": "",
    "Might": "0",
    "Accuracy": "0",
    "Critical": "0",
    "Dodge": "0",
    "RangeMin": "0",
    "RangeMax": "0",
    "str": "0",
    "int": "0",
    "dex": "0",
    "spd": "0",
    "luk": "0",
    "con": "0",
    "wis": "0",
    "AttackCount": "0",
    "RiposteCount": "0",
    "ftAttackCount": "0",
    "ftRiposteCount": "0",
    "AttackPriority": "0",
    "RipostePriority": "0",
    "ftAttackPriority": "0",
    "ftRipostePriority": "0",
    "SkillSuccess": "0",
    "GreatSkillSuccess": "0",
    "GreatSkillDamage": "0",
    "Effect": "Slayer-Light",
    "Slayer": "Light"
  },
  "Light": {
    "Name": "Light",
    "Description": "+1 SPD per Rune Level",
    "Weapon": "All",
    "Level": "1",
    "Max Level": "10",
    "Type": "",
    "Might": "0",
    "Accuracy": "0",
    "Critical": "0",
    "Dodge": "0",
    "RangeMin": "0",
    "RangeMax": "0",
    "str": "0",
    "int": "0",
    "dex": "0",
    "spd": "1lvl",
    "luk": "0",
    "con": "0",
    "wis": "0",
    "AttackCount": "0",
    "RiposteCount": "0",
    "ftAttackCount": "0",
    "ftRiposteCount": "0",
    "AttackPriority": "0",
    "RipostePriority": "0",
    "ftAttackPriority": "0",
    "ftRipostePriority": "0",
    "SkillSuccess": "0",
    "GreatSkillSuccess": "0",
    "GreatSkillDamage": "0",
    "Effect": "-",
    "Slayer": ""
  },
  "Slayer (Staff)": {
    "Name": "Slayer (Staff)",
    "Description": "Triple Weapon Might when using this weapon against an opponent with this Weapon",
    "Weapon": "All",
    "Level": "3",
    "Max Level": "3",
    "Type": "",
    "Might": "0",
    "Accuracy": "0",
    "Critical": "0",
    "Dodge": "0",
    "RangeMin": "0",
    "RangeMax": "0",
    "str": "0",
    "int": "0",
    "dex": "0",
    "spd": "0",
    "luk": "0",
    "con": "0",
    "wis": "0",
    "AttackCount": "0",
    "RiposteCount": "0",
    "ftAttackCount": "0",
    "ftRiposteCount": "0",
    "AttackPriority": "0",
    "RipostePriority": "0",
    "ftAttackPriority": "0",
    "ftRipostePriority": "0",
    "SkillSuccess": "0",
    "GreatSkillSuccess": "0",
    "GreatSkillDamage": "0",
    "Effect": "Slayer-Staff",
    "Slayer": "Staff"
  },
  "Wind Sword": {
    "Name": "Wind Sword",
    "Description": "Your Sword becomes Magic, Gains Range 1-2, and the special ability Slayer (Fly)",
    "Weapon": "Sword",
    "Level": "3",
    "Max Level": "3",
    "Type": "Magical",
    "Might": "0",
    "Accuracy": "0",
    "Critical": "0",
    "Dodge": "0",
    "RangeMin": "0",
    "RangeMax": "1",
    "str": "0",
    "int": "0",
    "dex": "0",
    "spd": "0",
    "luk": "0",
    "con": "0",
    "wis": "0",
    "AttackCount": "0",
    "RiposteCount": "0",
    "ftAttackCount": "0",
    "ftRiposteCount": "0",
    "AttackPriority": "0",
    "RipostePriority": "0",
    "ftAttackPriority": "0",
    "ftRipostePriority": "0",
    "SkillSuccess": "0",
    "GreatSkillSuccess": "0",
    "GreatSkillDamage": "0",
    "Effect": "Slayer-Fly",
    "Slayer": "Fly"
  },
  "Seeking": {
    "Name": "Seeking",
    "Description": "+5 Accuracy per Rune Level",
    "Weapon": "All",
    "Level": "1",
    "Max Level": "10",
    "Type": "",
    "Might": "0",
    "Accuracy": "5lvl",
    "Critical": "0",
    "Dodge": "0",
    "RangeMin": "0",
    "RangeMax": "0",
    "str": "0",
    "int": "0",
    "dex": "0",
    "spd": "0",
    "luk": "0",
    "con": "0",
    "wis": "0",
    "AttackCount": "0",
    "RiposteCount": "0",
    "ftAttackCount": "0",
    "ftRiposteCount": "0",
    "AttackPriority": "0",
    "RipostePriority": "0",
    "ftAttackPriority": "0",
    "ftRipostePriority": "0",
    "SkillSuccess": "0",
    "GreatSkillSuccess": "0",
    "GreatSkillDamage": "0",
    "Effect": "-",
    "Slayer": ""
  },
  "Slayer (Beast)": {
    "Name": "Slayer (Beast)",
    "Description": "Triple Weapon Might when using this weapon against an opponent with this Weapon",
    "Weapon": "All",
    "Level": "3",
    "Max Level": "3",
    "Type": "",
    "Might": "0",
    "Accuracy": "0",
    "Critical": "0",
    "Dodge": "0",
    "RangeMin": "0",
    "RangeMax": "0",
    "str": "0",
    "int": "0",
    "dex": "0",
    "spd": "0",
    "luk": "0",
    "con": "0",
    "wis": "0",
    "AttackCount": "0",
    "RiposteCount": "0",
    "ftAttackCount": "0",
    "ftRiposteCount": "0",
    "AttackPriority": "0",
    "RipostePriority": "0",
    "ftAttackPriority": "0",
    "ftRipostePriority": "0",
    "SkillSuccess": "0",
    "GreatSkillSuccess": "0",
    "GreatSkillDamage": "0",
    "Effect": "Slayer-Beast",
    "Slayer": "Beast"
  },
  "Slayer (Nobility)": {
    "Name": "Slayer (Nobility)",
    "Description": "Triple Weapon Might when using this weapon against an opponent with this Skill",
    "Weapon": "All",
    "Level": "2",
    "Max Level": "2",
    "Type": "",
    "Might": "0",
    "Accuracy": "0",
    "Critical": "0",
    "Dodge": "0",
    "RangeMin": "0",
    "RangeMax": "0",
    "str": "0",
    "int": "0",
    "dex": "0",
    "spd": "0",
    "luk": "0",
    "con": "0",
    "wis": "0",
    "AttackCount": "0",
    "RiposteCount": "0",
    "ftAttackCount": "0",
    "ftRiposteCount": "0",
    "AttackPriority": "0",
    "RipostePriority": "0",
    "ftAttackPriority": "0",
    "ftRipostePriority": "0",
    "SkillSuccess": "0",
    "GreatSkillSuccess": "0",
    "GreatSkillDamage": "0",
    "Effect": "Slayer-Nobility",
    "Slayer": "Nobility"
  },
  "Slayer (Dwarf)": {
    "Name": "Slayer (Dwarf)",
    "Description": "Triple Weapon Might when using this weapon against an opponent with this Creature Type",
    "Weapon": "All",
    "Level": "2",
    "Max Level": "2",
    "Type": "",
    "Might": "0",
    "Accuracy": "0",
    "Critical": "0",
    "Dodge": "0",
    "RangeMin": "0",
    "RangeMax": "0",
    "str": "0",
    "int": "0",
    "dex": "0",
    "spd": "0",
    "luk": "0",
    "con": "0",
    "wis": "0",
    "AttackCount": "0",
    "RiposteCount": "0",
    "ftAttackCount": "0",
    "ftRiposteCount": "0",
    "AttackPriority": "0",
    "RipostePriority": "0",
    "ftAttackPriority": "0",
    "ftRipostePriority": "0",
    "SkillSuccess": "0",
    "GreatSkillSuccess": "0",
    "GreatSkillDamage": "0",
    "Effect": "Slayer-Dwarf",
    "Slayer": "Dwarf"
  },
  "Shadow": {
    "Name": "Shadow",
    "Description": "Your Follow Through Attacks trigger immediately after your basic attacks",
    "Weapon": "All",
    "Level": "2",
    "Max Level": "2",
    "Type": "",
    "Might": "0",
    "Accuracy": "0",
    "Critical": "0",
    "Dodge": "0",
    "RangeMin": "0",
    "RangeMax": "0",
    "str": "0",
    "int": "0",
    "dex": "0",
    "spd": "0",
    "luk": "0",
    "con": "0",
    "wis": "0",
    "AttackCount": "0",
    "RiposteCount": "0",
    "ftAttackCount": "0",
    "ftRiposteCount": "0",
    "AttackPriority": "0",
    "RipostePriority": "0",
    "ftAttackPriority": "1",
    "ftRipostePriority": "1",
    "SkillSuccess": "0",
    "GreatSkillSuccess": "0",
    "GreatSkillDamage": "0",
    "Effect": "-",
    "Slayer": ""
  },
  "Defensive": {
    "Name": "Defensive",
    "Description": "+2 CON per Rune Level",
    "Weapon": "All",
    "Level": "1",
    "Max Level": "10",
    "Type": "",
    "Might": "0",
    "Accuracy": "0",
    "Critical": "0",
    "Dodge": "0",
    "RangeMin": "0",
    "RangeMax": "0",
    "str": "0",
    "int": "0",
    "dex": "0",
    "spd": "0",
    "luk": "0",
    "con": "2lvl",
    "wis": "0",
    "AttackCount": "0",
    "RiposteCount": "0",
    "ftAttackCount": "0",
    "ftRiposteCount": "0",
    "AttackPriority": "0",
    "RipostePriority": "0",
    "ftAttackPriority": "0",
    "ftRipostePriority": "0",
    "SkillSuccess": "0",
    "GreatSkillSuccess": "0",
    "GreatSkillDamage": "0",
    "Effect": "-",
    "Slayer": ""
  },
  "Slayer (Bow)": {
    "Name": "Slayer (Bow)",
    "Description": "Triple Weapon Might when using this weapon against an opponent with this Weapon",
    "Weapon": "All",
    "Level": "3",
    "Max Level": "3",
    "Type": "",
    "Might": "0",
    "Accuracy": "0",
    "Critical": "0",
    "Dodge": "0",
    "RangeMin": "0",
    "RangeMax": "0",
    "str": "0",
    "int": "0",
    "dex": "0",
    "spd": "0",
    "luk": "0",
    "con": "0",
    "wis": "0",
    "AttackCount": "0",
    "RiposteCount": "0",
    "ftAttackCount": "0",
    "ftRiposteCount": "0",
    "AttackPriority": "0",
    "RipostePriority": "0",
    "ftAttackPriority": "0",
    "ftRipostePriority": "0",
    "SkillSuccess": "0",
    "GreatSkillSuccess": "0",
    "GreatSkillDamage": "0",
    "Effect": "Slayer-Bow",
    "Slayer": "Bow"
  },
  "Slayer (Crossbow)": {
    "Name": "Slayer (Crossbow)",
    "Description": "Triple Weapon Might when using this weapon against an opponent with this Weapon",
    "Weapon": "All",
    "Level": "3",
    "Max Level": "3",
    "Type": "",
    "Might": "0",
    "Accuracy": "0",
    "Critical": "0",
    "Dodge": "0",
    "RangeMin": "0",
    "RangeMax": "0",
    "str": "0",
    "int": "0",
    "dex": "0",
    "spd": "0",
    "luk": "0",
    "con": "0",
    "wis": "0",
    "AttackCount": "0",
    "RiposteCount": "0",
    "ftAttackCount": "0",
    "ftRiposteCount": "0",
    "AttackPriority": "0",
    "RipostePriority": "0",
    "ftAttackPriority": "0",
    "ftRipostePriority": "0",
    "SkillSuccess": "0",
    "GreatSkillSuccess": "0",
    "GreatSkillDamage": "0",
    "Effect": "Slayer-Crossbow",
    "Slayer": "Crossbow"
  },
  "Slayer (Cyborg)": {
    "Name": "Slayer (Cyborg)",
    "Description": "Triple Weapon Might when using this weapon against an opponent with this Creature Type",
    "Weapon": "All",
    "Level": "2",
    "Max Level": "2",
    "Type": "",
    "Might": "0",
    "Accuracy": "0",
    "Critical": "0",
    "Dodge": "0",
    "RangeMin": "0",
    "RangeMax": "0",
    "str": "0",
    "int": "0",
    "dex": "0",
    "spd": "0",
    "luk": "0",
    "con": "0",
    "wis": "0",
    "AttackCount": "0",
    "RiposteCount": "0",
    "ftAttackCount": "0",
    "ftRiposteCount": "0",
    "AttackPriority": "0",
    "RipostePriority": "0",
    "ftAttackPriority": "0",
    "ftRipostePriority": "0",
    "SkillSuccess": "0",
    "GreatSkillSuccess": "0",
    "GreatSkillDamage": "0",
    "Effect": "Slayer-Cyborg",
    "Slayer": "Cyborg"
  },
  "Fortress": {
    "Name": "Fortress",
    "Description": "+1 CON and WIS per Rune Level",
    "Weapon": "All",
    "Level": "1",
    "Max Level": "10",
    "Type": "",
    "Might": "0",
    "Accuracy": "0",
    "Critical": "0",
    "Dodge": "0",
    "RangeMin": "0",
    "RangeMax": "0",
    "str": "0",
    "int": "0",
    "dex": "0",
    "spd": "0",
    "luk": "0",
    "con": "1lvl",
    "wis": "1lvl",
    "AttackCount": "0",
    "RiposteCount": "0",
    "ftAttackCount": "0",
    "ftRiposteCount": "0",
    "AttackPriority": "0",
    "RipostePriority": "0",
    "ftAttackPriority": "0",
    "ftRipostePriority": "0",
    "SkillSuccess": "0",
    "GreatSkillSuccess": "0",
    "GreatSkillDamage": "0",
    "Effect": "-",
    "Slayer": ""
  },
  "Slayer (Dragon)": {
    "Name": "Slayer (Dragon)",
    "Description": "Triple Weapon Might when using this weapon against an opponent with this Creature Type",
    "Weapon": "All",
    "Level": "2",
    "Max Level": "2",
    "Type": "",
    "Might": "0",
    "Accuracy": "0",
    "Critical": "0",
    "Dodge": "0",
    "RangeMin": "0",
    "RangeMax": "0",
    "str": "0",
    "int": "0",
    "dex": "0",
    "spd": "0",
    "luk": "0",
    "con": "0",
    "wis": "0",
    "AttackCount": "0",
    "RiposteCount": "0",
    "ftAttackCount": "0",
    "ftRiposteCount": "0",
    "AttackPriority": "0",
    "RipostePriority": "0",
    "ftAttackPriority": "0",
    "ftRipostePriority": "0",
    "SkillSuccess": "0",
    "GreatSkillSuccess": "0",
    "GreatSkillDamage": "0",
    "Effect": "Slayer-Dragon",
    "Slayer": "Dragon"
  },
  "Brave": {
    "Name": "Brave",
    "Description": "Your Attack and Follow Through Attack trigger twice. Lose 5 Speed and Might",
    "Weapon": "All",
    "Level": "2",
    "Max Level": "2",
    "Type": "",
    "Might": "-5",
    "Accuracy": "0",
    "Critical": "0",
    "Dodge": "0",
    "RangeMin": "0",
    "RangeMax": "0",
    "str": "0",
    "int": "0",
    "dex": "0",
    "spd": "-5",
    "luk": "0",
    "con": "0",
    "wis": "0",
    "AttackCount": "0",
    "RiposteCount": "0",
    "ftAttackCount": "1",
    "ftRiposteCount": "1",
    "AttackPriority": "0",
    "RipostePriority": "0",
    "ftAttackPriority": "0",
    "ftRipostePriority": "0",
    "SkillSuccess": "0",
    "GreatSkillSuccess": "0",
    "GreatSkillDamage": "0",
    "Effect": "-",
    "Slayer": ""
  },
  "Slayer (Lance)": {
    "Name": "Slayer (Lance)",
    "Description": "Triple Weapon Might when using this weapon against an opponent with this Weapon",
    "Weapon": "All",
    "Level": "3",
    "Max Level": "3",
    "Type": "",
    "Might": "0",
    "Accuracy": "0",
    "Critical": "0",
    "Dodge": "0",
    "RangeMin": "0",
    "RangeMax": "0",
    "str": "0",
    "int": "0",
    "dex": "0",
    "spd": "0",
    "luk": "0",
    "con": "0",
    "wis": "0",
    "AttackCount": "0",
    "RiposteCount": "0",
    "ftAttackCount": "0",
    "ftRiposteCount": "0",
    "AttackPriority": "0",
    "RipostePriority": "0",
    "ftAttackPriority": "0",
    "ftRipostePriority": "0",
    "SkillSuccess": "0",
    "GreatSkillSuccess": "0",
    "GreatSkillDamage": "0",
    "Effect": "Slayer-Lance",
    "Slayer": "Lance"
  },
  "Slayer (Herbivore)": {
    "Name": "Slayer (Herbivore)",
    "Description": "Triple Weapon Might when using this weapon against an opponent with this Creature Type",
    "Weapon": "All",
    "Level": "2",
    "Max Level": "2",
    "Type": "",
    "Might": "0",
    "Accuracy": "0",
    "Critical": "0",
    "Dodge": "0",
    "RangeMin": "0",
    "RangeMax": "0",
    "str": "0",
    "int": "0",
    "dex": "0",
    "spd": "0",
    "luk": "0",
    "con": "0",
    "wis": "0",
    "AttackCount": "0",
    "RiposteCount": "0",
    "ftAttackCount": "0",
    "ftRiposteCount": "0",
    "AttackPriority": "0",
    "RipostePriority": "0",
    "ftAttackPriority": "0",
    "ftRipostePriority": "0",
    "SkillSuccess": "0",
    "GreatSkillSuccess": "0",
    "GreatSkillDamage": "0",
    "Effect": "Slayer-Herbivore",
    "Slayer": "Herbivore"
  },
  "Bolt Axe": {
    "Name": "Bolt Axe",
    "Description": "Your Axe becomes Magic, Gains Range 1-2, and the special ability Slayer (Dragon)",
    "Weapon": "Axe",
    "Level": "3",
    "Max Level": "3",
    "Type": "Magical",
    "Might": "0",
    "Accuracy": "0",
    "Critical": "0",
    "Dodge": "0",
    "RangeMin": "0",
    "RangeMax": "1",
    "str": "0",
    "int": "0",
    "dex": "0",
    "spd": "0",
    "luk": "0",
    "con": "0",
    "wis": "0",
    "AttackCount": "0",
    "RiposteCount": "0",
    "ftAttackCount": "0",
    "ftRiposteCount": "0",
    "AttackPriority": "0",
    "RipostePriority": "0",
    "ftAttackPriority": "0",
    "ftRipostePriority": "0",
    "SkillSuccess": "0",
    "GreatSkillSuccess": "0",
    "GreatSkillDamage": "0",
    "Effect": "Slayer-Dragon",
    "Slayer": "Dragon"
  },
  "Throwing": {
    "Name": "Throwing",
    "Description": "Your weapon gains +1 Max Range, at the cost of 2 Might and 10 Accuracy",
    "Weapon": "Sword, Axe, Lance",
    "Level": "2",
    "Max Level": "2",
    "Type": "",
    "Might": "-2",
    "Accuracy": "-10",
    "Critical": "0",
    "Dodge": "0",
    "RangeMin": "0",
    "RangeMax": "1",
    "str": "0",
    "int": "0",
    "dex": "0",
    "spd": "0",
    "luk": "0",
    "con": "0",
    "wis": "0",
    "AttackCount": "0",
    "RiposteCount": "0",
    "ftAttackCount": "0",
    "ftRiposteCount": "0",
    "AttackPriority": "0",
    "RipostePriority": "0",
    "ftAttackPriority": "0",
    "ftRipostePriority": "0",
    "SkillSuccess": "0",
    "GreatSkillSuccess": "0",
    "GreatSkillDamage": "0",
    "Effect": "-",
    "Slayer": ""
  },
  "Mighty": {
    "Name": "Mighty",
    "Description": "Great Skills that have a %chance of activation get +5% per Rune Level, and Great Skills that deal damage deal +2 Damage per rune level when they trigger",
    "Weapon": "All",
    "Level": "5",
    "Max Level": "10",
    "Type": "",
    "Might": "0",
    "Accuracy": "0",
    "Critical": "0",
    "Dodge": "0",
    "RangeMin": "0",
    "RangeMax": "0",
    "str": "0",
    "int": "0",
    "dex": "0",
    "spd": "0",
    "luk": "0",
    "con": "0",
    "wis": "0",
    "AttackCount": "0",
    "RiposteCount": "0",
    "ftAttackCount": "0",
    "ftRiposteCount": "0",
    "AttackPriority": "0",
    "RipostePriority": "0",
    "ftAttackPriority": "0",
    "ftRipostePriority": "0",
    "SkillSuccess": "0",
    "GreatSkillSuccess": "0.05lvl",
    "GreatSkillDamage": "2lvl",
    "Effect": "-",
    "Slayer": "-"
  },
  "Evasive": {
    "Name": "Evasive",
    "Description": "+5 Dodge per Rune Level",
    "Weapon": "All",
    "Level": "1",
    "Max Level": "10",
    "Type": "",
    "Might": "0",
    "Accuracy": "0",
    "Critical": "0",
    "Dodge": "5lvl",
    "RangeMin": "0",
    "RangeMax": "0",
    "str": "0",
    "int": "0",
    "dex": "0",
    "spd": "0",
    "luk": "0",
    "con": "0",
    "wis": "0",
    "AttackCount": "0",
    "RiposteCount": "0",
    "ftAttackCount": "0",
    "ftRiposteCount": "0",
    "AttackPriority": "0",
    "RipostePriority": "0",
    "ftAttackPriority": "0",
    "ftRipostePriority": "0",
    "SkillSuccess": "0",
    "GreatSkillSuccess": "0",
    "GreatSkillDamage": "0",
    "Effect": "-",
    "Slayer": ""
  },
  "Resistant": {
    "Name": "Resistant",
    "Description": "+2 WIS per Rune Level",
    "Weapon": "All",
    "Level": "1",
    "Max Level": "10",
    "Type": "",
    "Might": "0",
    "Accuracy": "0",
    "Critical": "0",
    "Dodge": "0",
    "RangeMin": "0",
    "RangeMax": "0",
    "str": "0",
    "int": "0",
    "dex": "0",
    "spd": "0",
    "luk": "0",
    "con": "0",
    "wis": "2lvl",
    "AttackCount": "0",
    "RiposteCount": "0",
    "ftAttackCount": "0",
    "ftRiposteCount": "0",
    "AttackPriority": "0",
    "RipostePriority": "0",
    "ftAttackPriority": "0",
    "ftRipostePriority": "0",
    "SkillSuccess": "0",
    "GreatSkillSuccess": "0",
    "GreatSkillDamage": "0",
    "Effect": "-",
    "Slayer": ""
  },
  "Slayer (Elf)": {
    "Name": "Slayer (Elf)",
    "Description": "Triple Weapon Might when using this weapon against an opponent with this Creature Type",
    "Weapon": "All",
    "Level": "2",
    "Max Level": "2",
    "Type": "",
    "Might": "0",
    "Accuracy": "0",
    "Critical": "0",
    "Dodge": "0",
    "RangeMin": "0",
    "RangeMax": "0",
    "str": "0",
    "int": "0",
    "dex": "0",
    "spd": "0",
    "luk": "0",
    "con": "0",
    "wis": "0",
    "AttackCount": "0",
    "RiposteCount": "0",
    "ftAttackCount": "0",
    "ftRiposteCount": "0",
    "AttackPriority": "0",
    "RipostePriority": "0",
    "ftAttackPriority": "0",
    "ftRipostePriority": "0",
    "SkillSuccess": "0",
    "GreatSkillSuccess": "0",
    "GreatSkillDamage": "0",
    "Effect": "Slayer-Elf",
    "Slayer": "Elf"
  },
  "Slayer (Armored)": {
    "Name": "Slayer (Armored)",
    "Description": "Triple Weapon Might when using this weapon against an opponent with this Skill",
    "Weapon": "All",
    "Level": "2",
    "Max Level": "2",
    "Type": "",
    "Might": "0",
    "Accuracy": "0",
    "Critical": "0",
    "Dodge": "0",
    "RangeMin": "0",
    "RangeMax": "0",
    "str": "0",
    "int": "0",
    "dex": "0",
    "spd": "0",
    "luk": "0",
    "con": "0",
    "wis": "0",
    "AttackCount": "0",
    "RiposteCount": "0",
    "ftAttackCount": "0",
    "ftRiposteCount": "0",
    "AttackPriority": "0",
    "RipostePriority": "0",
    "ftAttackPriority": "0",
    "ftRipostePriority": "0",
    "SkillSuccess": "0",
    "GreatSkillSuccess": "0",
    "GreatSkillDamage": "0",
    "Effect": "Slayer-Armored",
    "Slayer": "Armored"
  },
  "Slayer (Human)": {
    "Name": "Slayer (Human)",
    "Description": "Triple Weapon Might when using this weapon against an opponent with this Creature Type",
    "Weapon": "All",
    "Level": "2",
    "Max Level": "2",
    "Type": "",
    "Might": "0",
    "Accuracy": "0",
    "Critical": "0",
    "Dodge": "0",
    "RangeMin": "0",
    "RangeMax": "0",
    "str": "0",
    "int": "0",
    "dex": "0",
    "spd": "0",
    "luk": "0",
    "con": "0",
    "wis": "0",
    "AttackCount": "0",
    "RiposteCount": "0",
    "ftAttackCount": "0",
    "ftRiposteCount": "0",
    "AttackPriority": "0",
    "RipostePriority": "0",
    "ftAttackPriority": "0",
    "ftRipostePriority": "0",
    "SkillSuccess": "0",
    "GreatSkillSuccess": "0",
    "GreatSkillDamage": "0",
    "Effect": "Slayer-Human",
    "Slayer": "Human"
  },
  "Slayer (Sing)": {
    "Name": "Slayer (Sing)",
    "Description": "Triple Weapon Might when using this weapon against an opponent with this Skill",
    "Weapon": "All",
    "Level": "2",
    "Max Level": "2",
    "Type": "",
    "Might": "0",
    "Accuracy": "0",
    "Critical": "0",
    "Dodge": "0",
    "RangeMin": "0",
    "RangeMax": "0",
    "str": "0",
    "int": "0",
    "dex": "0",
    "spd": "0",
    "luk": "0",
    "con": "0",
    "wis": "0",
    "AttackCount": "0",
    "RiposteCount": "0",
    "ftAttackCount": "0",
    "ftRiposteCount": "0",
    "AttackPriority": "0",
    "RipostePriority": "0",
    "ftAttackPriority": "0",
    "ftRipostePriority": "0",
    "SkillSuccess": "0",
    "GreatSkillSuccess": "0",
    "GreatSkillDamage": "0",
    "Effect": "Slayer-Sing",
    "Slayer": "Sing"
  },
  "Slayer (Runed)": {
    "Name": "Slayer (Runed)",
    "Description": "Triple Weapon Might when using this weapon against an opponent with this Skill",
    "Weapon": "All",
    "Level": "2",
    "Max Level": "2",
    "Type": "",
    "Might": "0",
    "Accuracy": "0",
    "Critical": "0",
    "Dodge": "0",
    "RangeMin": "0",
    "RangeMax": "0",
    "str": "0",
    "int": "0",
    "dex": "0",
    "spd": "0",
    "luk": "0",
    "con": "0",
    "wis": "0",
    "AttackCount": "0",
    "RiposteCount": "0",
    "ftAttackCount": "0",
    "ftRiposteCount": "0",
    "AttackPriority": "0",
    "RipostePriority": "0",
    "ftAttackPriority": "0",
    "ftRipostePriority": "0",
    "SkillSuccess": "0",
    "GreatSkillSuccess": "0",
    "GreatSkillDamage": "0",
    "Effect": "Slayer-Runed",
    "Slayer": "Runed"
  },
  "Sweep": {
    "Name": "Sweep",
    "Description": "Neither you nor your opponent can Follow Through Attack or Riposte",
    "Weapon": "All",
    "Level": "2",
    "Max Level": "2",
    "Type": "",
    "Might": "0",
    "Accuracy": "0",
    "Critical": "0",
    "Dodge": "0",
    "RangeMin": "0",
    "RangeMax": "0",
    "str": "0",
    "int": "0",
    "dex": "0",
    "spd": "0",
    "luk": "0",
    "con": "0",
    "wis": "0",
    "AttackCount": "0",
    "RiposteCount": "0",
    "ftAttackCount": "0",
    "ftRiposteCount": "0",
    "AttackPriority": "0",
    "RipostePriority": "0",
    "ftAttackPriority": "0",
    "ftRipostePriority": "0",
    "SkillSuccess": "0",
    "GreatSkillSuccess": "0",
    "GreatSkillDamage": "0",
    "Effect": "Sweep",
    "Slayer": ""
  },
  "Fire Lance": {
    "Name": "Fire Lance",
    "Description": "Your Lance becomes Magic, Gains Range 1-2, and the special ability Slayer (Carnivore) and Slayer (Herbivore)",
    "Weapon": "Lance",
    "Level": "3",
    "Max Level": "3",
    "Type": "Magical",
    "Might": "0",
    "Accuracy": "0",
    "Critical": "0",
    "Dodge": "0",
    "RangeMin": "0",
    "RangeMax": "1",
    "str": "0",
    "int": "0",
    "dex": "0",
    "spd": "0",
    "luk": "0",
    "con": "0",
    "wis": "0",
    "AttackCount": "0",
    "RiposteCount": "0",
    "ftAttackCount": "0",
    "ftRiposteCount": "0",
    "AttackPriority": "0",
    "RipostePriority": "0",
    "ftAttackPriority": "0",
    "ftRipostePriority": "0",
    "SkillSuccess": "0",
    "GreatSkillSuccess": "0",
    "GreatSkillDamage": "0",
    "Effect": "Slayer-Carnivore|Slayer-Herbivore",
    "Slayer": "Carnivore|Herbivore"
  },
  "Wicked": {
    "Name": "Wicked",
    "Description": "+5 Critical per Rune Level",
    "Weapon": "All",
    "Level": "1",
    "Max Level": "10",
    "Type": "",
    "Might": "0",
    "Accuracy": "0",
    "Critical": "5lvl",
    "Dodge": "0",
    "RangeMin": "0",
    "RangeMax": "0",
    "str": "0",
    "int": "0",
    "dex": "0",
    "spd": "0",
    "luk": "0",
    "con": "0",
    "wis": "0",
    "AttackCount": "0",
    "RiposteCount": "0",
    "ftAttackCount": "0",
    "ftRiposteCount": "0",
    "AttackPriority": "0",
    "RipostePriority": "0",
    "ftAttackPriority": "0",
    "ftRipostePriority": "0",
    "SkillSuccess": "0",
    "GreatSkillSuccess": "0",
    "GreatSkillDamage": "0",
    "Effect": "-",
    "Slayer": ""
  },
  "Slayer (Carnivore)": {
    "Name": "Slayer (Carnivore)",
    "Description": "Triple Weapon Might when using this weapon against an opponent with this Creature Type",
    "Weapon": "All",
    "Level": "2",
    "Max Level": "2",
    "Type": "",
    "Might": "0",
    "Accuracy": "0",
    "Critical": "0",
    "Dodge": "0",
    "RangeMin": "0",
    "RangeMax": "0",
    "str": "0",
    "int": "0",
    "dex": "0",
    "spd": "0",
    "luk": "0",
    "con": "0",
    "wis": "0",
    "AttackCount": "0",
    "RiposteCount": "0",
    "ftAttackCount": "0",
    "ftRiposteCount": "0",
    "AttackPriority": "0",
    "RipostePriority": "0",
    "ftAttackPriority": "0",
    "ftRipostePriority": "0",
    "SkillSuccess": "0",
    "GreatSkillSuccess": "0",
    "GreatSkillDamage": "0",
    "Effect": "Slayer-Carnivore",
    "Slayer": "Carnivore"
  },
  "Slayer (Knives)": {
    "Name": "Slayer (Knives)",
    "Description": "Triple Weapon Might when using this weapon against an opponent with this Weapon",
    "Weapon": "All",
    "Level": "3",
    "Max Level": "3",
    "Type": "",
    "Might": "0",
    "Accuracy": "0",
    "Critical": "0",
    "Dodge": "0",
    "RangeMin": "0",
    "RangeMax": "0",
    "str": "0",
    "int": "0",
    "dex": "0",
    "spd": "0",
    "luk": "0",
    "con": "0",
    "wis": "0",
    "AttackCount": "0",
    "RiposteCount": "0",
    "ftAttackCount": "0",
    "ftRiposteCount": "0",
    "AttackPriority": "0",
    "RipostePriority": "0",
    "ftAttackPriority": "0",
    "ftRipostePriority": "0",
    "SkillSuccess": "0",
    "GreatSkillSuccess": "0",
    "GreatSkillDamage": "0",
    "Effect": "Slayer-Knives",
    "Slayer": "Knives"
  },
  "Slayer (Flintlock)": {
    "Name": "Slayer (Flintlock)",
    "Description": "Triple Weapon Might when using this weapon against an opponent with this Weapon",
    "Weapon": "All",
    "Level": "3",
    "Max Level": "3",
    "Type": "",
    "Might": "0",
    "Accuracy": "0",
    "Critical": "0",
    "Dodge": "0",
    "RangeMin": "0",
    "RangeMax": "0",
    "str": "0",
    "int": "0",
    "dex": "0",
    "spd": "0",
    "luk": "0",
    "con": "0",
    "wis": "0",
    "AttackCount": "0",
    "RiposteCount": "0",
    "ftAttackCount": "0",
    "ftRiposteCount": "0",
    "AttackPriority": "0",
    "RipostePriority": "0",
    "ftAttackPriority": "0",
    "ftRipostePriority": "0",
    "SkillSuccess": "0",
    "GreatSkillSuccess": "0",
    "GreatSkillDamage": "0",
    "Effect": "Slayer-Flintlock",
    "Slayer": "Flintlock"
  },
  "Slayer (Gauntlet)": {
    "Name": "Slayer (Gauntlet)",
    "Description": "Triple Weapon Might when using this weapon against an opponent with this Weapon",
    "Weapon": "All",
    "Level": "3",
    "Max Level": "3",
    "Type": "",
    "Might": "0",
    "Accuracy": "0",
    "Critical": "0",
    "Dodge": "0",
    "RangeMin": "0",
    "RangeMax": "0",
    "str": "0",
    "int": "0",
    "dex": "0",
    "spd": "0",
    "luk": "0",
    "con": "0",
    "wis": "0",
    "AttackCount": "0",
    "RiposteCount": "0",
    "ftAttackCount": "0",
    "ftRiposteCount": "0",
    "AttackPriority": "0",
    "RipostePriority": "0",
    "ftAttackPriority": "0",
    "ftRipostePriority": "0",
    "SkillSuccess": "0",
    "GreatSkillSuccess": "0",
    "GreatSkillDamage": "0",
    "Effect": "Slayer-Gauntlet",
    "Slayer": "Gauntlet"
  },
  "Slayer (Goblin)": {
    "Name": "Slayer (Goblin)",
    "Description": "Triple Weapon Might when using this weapon against an opponent with this Creature Type",
    "Weapon": "All",
    "Level": "2",
    "Max Level": "2",
    "Type": "",
    "Might": "0",
    "Accuracy": "0",
    "Critical": "0",
    "Dodge": "0",
    "RangeMin": "0",
    "RangeMax": "0",
    "str": "0",
    "int": "0",
    "dex": "0",
    "spd": "0",
    "luk": "0",
    "con": "0",
    "wis": "0",
    "AttackCount": "0",
    "RiposteCount": "0",
    "ftAttackCount": "0",
    "ftRiposteCount": "0",
    "AttackPriority": "0",
    "RipostePriority": "0",
    "ftAttackPriority": "0",
    "ftRipostePriority": "0",
    "SkillSuccess": "0",
    "GreatSkillSuccess": "0",
    "GreatSkillDamage": "0",
    "Effect": "Slayer-Goblin",
    "Slayer": "Goblin"
  },
  "Slayer (Orc)": {
    "Name": "Slayer (Orc)",
    "Description": "Triple Weapon Might when using this weapon against an opponent with this Creature Type",
    "Weapon": "All",
    "Level": "2",
    "Max Level": "2",
    "Type": "",
    "Might": "0",
    "Accuracy": "0",
    "Critical": "0",
    "Dodge": "0",
    "RangeMin": "0",
    "RangeMax": "0",
    "str": "0",
    "int": "0",
    "dex": "0",
    "spd": "0",
    "luk": "0",
    "con": "0",
    "wis": "0",
    "AttackCount": "0",
    "RiposteCount": "0",
    "ftAttackCount": "0",
    "ftRiposteCount": "0",
    "AttackPriority": "0",
    "RipostePriority": "0",
    "ftAttackPriority": "0",
    "ftRipostePriority": "0",
    "SkillSuccess": "0",
    "GreatSkillSuccess": "0",
    "GreatSkillDamage": "0",
    "Effect": "Slayer-Orc",
    "Slayer": "Orc"
  },
  "Slayer (Wind)": {
    "Name": "Slayer (Wind)",
    "Description": "Triple Weapon Might when using this weapon against an opponent with this Weapon",
    "Weapon": "All",
    "Level": "3",
    "Max Level": "3",
    "Type": "",
    "Might": "0",
    "Accuracy": "0",
    "Critical": "0",
    "Dodge": "0",
    "RangeMin": "0",
    "RangeMax": "0",
    "str": "0",
    "int": "0",
    "dex": "0",
    "spd": "0",
    "luk": "0",
    "con": "0",
    "wis": "0",
    "AttackCount": "0",
    "RiposteCount": "0",
    "ftAttackCount": "0",
    "ftRiposteCount": "0",
    "AttackPriority": "0",
    "RipostePriority": "0",
    "ftAttackPriority": "0",
    "ftRipostePriority": "0",
    "SkillSuccess": "0",
    "GreatSkillSuccess": "0",
    "GreatSkillDamage": "0",
    "Effect": "Slayer-Wind",
    "Slayer": "Wind"
  },
  "Conquerer": {
    "Name": "Conquerer",
    "Description": "When you are attacked without the ability to Counter Attack, reduce damage taken by 10% per Rune Level",
    "Weapon": "All",
    "Level": "3",
    "Max Level": "10",
    "Type": "",
    "Might": "0",
    "Accuracy": "0",
    "Critical": "0",
    "Dodge": "0",
    "RangeMin": "0",
    "RangeMax": "0",
    "str": "0",
    "int": "0",
    "dex": "0",
    "spd": "0",
    "luk": "0",
    "con": "0",
    "wis": "0",
    "AttackCount": "0",
    "RiposteCount": "0",
    "ftAttackCount": "0",
    "ftRiposteCount": "0",
    "AttackPriority": "0",
    "RipostePriority": "0",
    "ftAttackPriority": "0",
    "ftRipostePriority": "0",
    "SkillSuccess": "0",
    "GreatSkillSuccess": "0",
    "GreatSkillDamage": "0",
    "Effect": "Conquerer-0.1lvl",
    "Slayer": ""
  },
  "Masterwork": {
    "Name": "Masterwork",
    "Description": "Skills that have a %chance of activation get +5% per Rune Level",
    "Weapon": "All",
    "Level": "2",
    "Max Level": "10",
    "Type": "",
    "Might": "0",
    "Accuracy": "0",
    "Critical": "0",
    "Dodge": "0",
    "RangeMin": "0",
    "RangeMax": "0",
    "str": "0",
    "int": "0",
    "dex": "0",
    "spd": "0",
    "luk": "0",
    "con": "0",
    "wis": "0",
    "AttackCount": "0",
    "RiposteCount": "0",
    "ftAttackCount": "0",
    "ftRiposteCount": "0",
    "AttackPriority": "0",
    "RipostePriority": "0",
    "ftAttackPriority": "0",
    "ftRipostePriority": "0",
    "SkillSuccess": "0.05lvl",
    "GreatSkillSuccess": "0",
    "GreatSkillDamage": "0",
    "Effect": "-",
    "Slayer": "-"
  },
  "Blessed": {
    "Name": "Blessed",
    "Description": "At the start of your turn, recover 3 HP per Rune Level",
    "Weapon": "All",
    "Level": "1",
    "Max Level": "10",
    "Type": "",
    "Might": "0",
    "Accuracy": "0",
    "Critical": "0",
    "Dodge": "0",
    "RangeMin": "0",
    "RangeMax": "0",
    "str": "0",
    "int": "0",
    "dex": "0",
    "spd": "0",
    "luk": "0",
    "con": "0",
    "wis": "0",
    "AttackCount": "0",
    "RiposteCount": "0",
    "ftAttackCount": "0",
    "ftRiposteCount": "0",
    "AttackPriority": "0",
    "RipostePriority": "0",
    "ftAttackPriority": "0",
    "ftRipostePriority": "0",
    "SkillSuccess": "0",
    "GreatSkillSuccess": "0",
    "GreatSkillDamage": "0",
    "Effect": "-",
    "Slayer": ""
  },
  "Slayer (Fly)": {
    "Name": "Slayer (Fly)",
    "Description": "Triple Weapon Might when using this weapon against an opponent with this Skill",
    "Weapon": "All",
    "Level": "2",
    "Max Level": "2",
    "Type": "",
    "Might": "0",
    "Accuracy": "0",
    "Critical": "0",
    "Dodge": "0",
    "RangeMin": "0",
    "RangeMax": "0",
    "str": "0",
    "int": "0",
    "dex": "0",
    "spd": "0",
    "luk": "0",
    "con": "0",
    "wis": "0",
    "AttackCount": "0",
    "RiposteCount": "0",
    "ftAttackCount": "0",
    "ftRiposteCount": "0",
    "AttackPriority": "0",
    "RipostePriority": "0",
    "ftAttackPriority": "0",
    "ftRipostePriority": "0",
    "SkillSuccess": "0",
    "GreatSkillSuccess": "0",
    "GreatSkillDamage": "0",
    "Effect": "Slayer-Fly",
    "Slayer": "Fly"
  },
  "Hero": {
    "Name": "Hero",
    "Description": "Your Attacks, Follow Through Attacks, Ripostes, and Follow through Ripostes trigger twice in a row. -5 Might and -5 Speed",
    "Weapon": "All",
    "Level": "4",
    "Max Level": "4",
    "Type": "",
    "Might": "-5",
    "Accuracy": "0",
    "Critical": "0",
    "Dodge": "0",
    "RangeMin": "0",
    "RangeMax": "0",
    "str": "0",
    "int": "0",
    "dex": "0",
    "spd": "-5",
    "luk": "0",
    "con": "0",
    "wis": "0",
    "AttackCount": "1",
    "RiposteCount": "1",
    "ftAttackCount": "1",
    "ftRiposteCount": "1",
    "AttackPriority": "0",
    "RipostePriority": "0",
    "ftAttackPriority": "0",
    "ftRipostePriority": "0",
    "SkillSuccess": "0",
    "GreatSkillSuccess": "0",
    "GreatSkillDamage": "0",
    "Effect": "-",
    "Slayer": "-"
  },
  "Slayer (Sword)": {
    "Name": "Slayer (Sword)",
    "Description": "Triple Weapon Might when using this weapon against an opponent with this Weapon",
    "Weapon": "All",
    "Level": "3",
    "Max Level": "3",
    "Type": "",
    "Might": "0",
    "Accuracy": "0",
    "Critical": "0",
    "Dodge": "0",
    "RangeMin": "0",
    "RangeMax": "0",
    "str": "0",
    "int": "0",
    "dex": "0",
    "spd": "0",
    "luk": "0",
    "con": "0",
    "wis": "0",
    "AttackCount": "0",
    "RiposteCount": "0",
    "ftAttackCount": "0",
    "ftRiposteCount": "0",
    "AttackPriority": "0",
    "RipostePriority": "0",
    "ftAttackPriority": "0",
    "ftRipostePriority": "0",
    "SkillSuccess": "0",
    "GreatSkillSuccess": "0",
    "GreatSkillDamage": "0",
    "Effect": "Slayer-Sword",
    "Slayer": "Sword"
  },
  "Slayer (Fire)": {
    "Name": "Slayer (Fire)",
    "Description": "Triple Weapon Might when using this weapon against an opponent with this Weapon",
    "Weapon": "All",
    "Level": "3",
    "Max Level": "3",
    "Type": "",
    "Might": "0",
    "Accuracy": "0",
    "Critical": "0",
    "Dodge": "0",
    "RangeMin": "0",
    "RangeMax": "0",
    "str": "0",
    "int": "0",
    "dex": "0",
    "spd": "0",
    "luk": "0",
    "con": "0",
    "wis": "0",
    "AttackCount": "0",
    "RiposteCount": "0",
    "ftAttackCount": "0",
    "ftRiposteCount": "0",
    "AttackPriority": "0",
    "RipostePriority": "0",
    "ftAttackPriority": "0",
    "ftRipostePriority": "0",
    "SkillSuccess": "0",
    "GreatSkillSuccess": "0",
    "GreatSkillDamage": "0",
    "Effect": "Slayer-Fire",
    "Slayer": "Fire"
  },
  "Heavy": {
    "Name": "Heavy",
    "Description": "+1 Might per Rune Level",
    "Weapon": "All",
    "Level": "1",
    "Max Level": "10",
    "Type": "",
    "Might": "1lvl",
    "Accuracy": "0",
    "Critical": "0",
    "Dodge": "0",
    "RangeMin": "0",
    "RangeMax": "0",
    "str": "0",
    "int": "0",
    "dex": "0",
    "spd": "0",
    "luk": "0",
    "con": "0",
    "wis": "0",
    "AttackCount": "0",
    "RiposteCount": "0",
    "ftAttackCount": "0",
    "ftRiposteCount": "0",
    "AttackPriority": "0",
    "RipostePriority": "0",
    "ftAttackPriority": "0",
    "ftRipostePriority": "0",
    "SkillSuccess": "0",
    "GreatSkillSuccess": "0",
    "GreatSkillDamage": "0",
    "Effect": "-",
    "Slayer": ""
  }
}
